<?xml version="1.0" encoding="ISO-8859-1"?>
<!--********************************************-->
<!--* FIORILLI SOFTWARE LTDA                   *-->
<!--* SISTEMA INTEGRADO DE PESSOAL             *-->
<!--* GERADO 22/11/2023 17:02:51               *-->
<!--* VERSAO 7.5.378.19.17173/R                *-->
<!--* USUARIO PC CONTREINA                     *-->
<!--* DOMINIO MCT                              *-->
<!--* NOME PC SERVER                           *-->
<!--* USUARIO SISTEMA contreina                *-->
<!--********************************************-->
<aux:CadastrosAuxiliaresSagresFolha xmlns:fol="http://www.tce.pi.gov.br/sagres2023/xml/folhaPagamento" xmlns:aux="http://www.tce.pi.gov.br/sagres2023/xml/cadastrosAuxiliaresSagresFolha" xmlns:gen="http://www.tce.pi.gov.br/sagres2023/xml/genericos" xmlns:tab="http://www.tce.pi.gov.br/sagres2023/xml/tabelasInternas">
  <aux:PrestacaoContas>
    <aux:codigoUnidGestora>201133</aux:codigoUnidGestora>
    <aux:nomeUnidGestora>P. M. DE MORRO CABECA NO TEMPO</aux:nomeUnidGestora>
    <aux:cpfContador>01340944332</aux:cpfContador>
    <aux:cpfGestor>82387796349</aux:cpfGestor>
    <aux:anoReferencia>2023</aux:anoReferencia>
    <aux:mesReferencia>9</aux:mesReferencia>
    <aux:versaoXml>19</aux:versaoXml>
    <aux:diaInicPresContas>1</aux:diaInicPresContas>
    <aux:diaFinaPresContas>30</aux:diaFinaPresContas>
  </aux:PrestacaoContas>
  <aux:Servidor>
    <aux:matricula>000000000000973</aux:matricula>
    <aux:cpfServidor>50016506820</aux:cpfServidor>
    <aux:rgServidor>561948355</aux:rgServidor>
    <aux:orgaoExpedidor>SSPSP</aux:orgaoExpedidor>
    <aux:dataExpeCartDeIdentidade>2020-11-30</aux:dataExpeCartDeIdentidade>
    <aux:nomeServidor>MEKALINE DUARTE DE FIGUEIREDO</aux:nomeServidor>
    <aux:dataNascimento>2003-06-15</aux:dataNascimento>
    <aux:sexo>2</aux:sexo>
    <aux:tituloEleitor>000046871281546</aux:tituloEleitor>
    <aux:tipoEstaCivil>1</aux:tipoEstaCivil>
    <aux:pisPAsep>000023813159503</aux:pisPAsep>
    <aux:numeroOrgaoClasse>00000000</aux:numeroOrgaoClasse>
    <aux:cpfPai>25332860870</aux:cpfPai>
    <aux:nomePai>FRANCISCO MENDES DE FIGUEIREDO</aux:nomePai>
    <aux:cpfMae>26929215856</aux:cpfMae>
    <aux:nomeMae>MARIA APARECIDA DUARTE MENDES</aux:nomeMae>
  </aux:Servidor>
  <aux:Servidor>
    <aux:matricula>000000000000974</aux:matricula>
    <aux:cpfServidor>10119773384</aux:cpfServidor>
    <aux:rgServidor>664224568</aux:rgServidor>
    <aux:orgaoExpedidor>SSPPI</aux:orgaoExpedidor>
    <aux:dataExpeCartDeIdentidade>2019-11-12</aux:dataExpeCartDeIdentidade>
    <aux:nomeServidor>ROBERTA DIAS ALVES</aux:nomeServidor>
    <aux:dataNascimento>2005-01-08</aux:dataNascimento>
    <aux:sexo>2</aux:sexo>
    <aux:tituloEleitor>000048418651503</aux:tituloEleitor>
    <aux:tipoEstaCivil>1</aux:tipoEstaCivil>
    <aux:pisPAsep>000021306355003</aux:pisPAsep>
    <aux:numeroOrgaoClasse>00000000</aux:numeroOrgaoClasse>
    <aux:cpfPai>99999999999</aux:cpfPai>
    <aux:nomePai>MESSIAS DUARTE ALVES</aux:nomePai>
    <aux:cpfMae>02939024375</aux:cpfMae>
    <aux:nomeMae>CLESIANE DIAS ALVES</aux:nomeMae>
  </aux:Servidor>
  <aux:Servidor>
    <aux:matricula>000000000000975</aux:matricula>
    <aux:cpfServidor>08015339375</aux:cpfServidor>
    <aux:rgServidor>56057373</aux:rgServidor>
    <aux:orgaoExpedidor>SSPSP</aux:orgaoExpedidor>
    <aux:dataExpeCartDeIdentidade>2020-01-01</aux:dataExpeCartDeIdentidade>
    <aux:nomeServidor>IURE ALVES</aux:nomeServidor>
    <aux:dataNascimento>1997-10-09</aux:dataNascimento>
    <aux:sexo>1</aux:sexo>
    <aux:tituloEleitor>000042744391538</aux:tituloEleitor>
    <aux:tipoEstaCivil>1</aux:tipoEstaCivil>
    <aux:pisPAsep>000016304200928</aux:pisPAsep>
    <aux:numeroOrgaoClasse>00000000</aux:numeroOrgaoClasse>
    <aux:cpfPai>99999999999</aux:cpfPai>
    <aux:nomePai>Sem Nome</aux:nomePai>
    <aux:cpfMae>27773852898</aux:cpfMae>
    <aux:nomeMae>SINDELANJA ALVES</aux:nomeMae>
  </aux:Servidor>
  <aux:Servidor>
    <aux:matricula>000000000000977</aux:matricula>
    <aux:cpfServidor>05279664367</aux:cpfServidor>
    <aux:rgServidor>3446526</aux:rgServidor>
    <aux:orgaoExpedidor>SSPPI</aux:orgaoExpedidor>
    <aux:dataExpeCartDeIdentidade>2010-04-28</aux:dataExpeCartDeIdentidade>
    <aux:nomeServidor>ORLEIDE JUREMA LOPES</aux:nomeServidor>
    <aux:dataNascimento>1983-09-21</aux:dataNascimento>
    <aux:sexo>1</aux:sexo>
    <aux:tituloEleitor>000030694991503</aux:tituloEleitor>
    <aux:tipoEstaCivil>2</aux:tipoEstaCivil>
    <aux:pisPAsep>000016685371251</aux:pisPAsep>
    <aux:numeroOrgaoClasse>00000000</aux:numeroOrgaoClasse>
    <aux:cpfPai>22386319172</aux:cpfPai>
    <aux:nomePai>JOÃO MATIAS LOPES</aux:nomePai>
    <aux:cpfMae>01257819542</aux:cpfMae>
    <aux:nomeMae>FRANCISCA JUREMA LOPES</aux:nomeMae>
  </aux:Servidor>
  <aux:Servidor>
    <aux:matricula>000000000000979</aux:matricula>
    <aux:cpfServidor>01537564544</aux:cpfServidor>
    <aux:rgServidor>134702433</aux:rgServidor>
    <aux:orgaoExpedidor>SSPPI</aux:orgaoExpedidor>
    <aux:dataExpeCartDeIdentidade>2000-01-01</aux:dataExpeCartDeIdentidade>
    <aux:nomeServidor>ORLEIDE JUREMA LOPES</aux:nomeServidor>
    <aux:dataNascimento>1981-08-21</aux:dataNascimento>
    <aux:sexo>1</aux:sexo>
    <aux:tituloEleitor>000080132350590</aux:tituloEleitor>
    <aux:tipoEstaCivil>2</aux:tipoEstaCivil>
    <aux:pisPAsep>000020406354132</aux:pisPAsep>
    <aux:numeroOrgaoClasse>00000000</aux:numeroOrgaoClasse>
    <aux:cpfPai>22386319172</aux:cpfPai>
    <aux:nomePai>JOÃO MATIAS LOPES</aux:nomePai>
    <aux:cpfMae>01257819542</aux:cpfMae>
    <aux:nomeMae>FRANCISCA JUREMA LOPES</aux:nomeMae>
  </aux:Servidor>
  <aux:Servidor>
    <aux:matricula>000000000000980</aux:matricula>
    <aux:cpfServidor>05081061336</aux:cpfServidor>
    <aux:rgServidor>597086965</aux:rgServidor>
    <aux:orgaoExpedidor>SSPSP</aux:orgaoExpedidor>
    <aux:dataExpeCartDeIdentidade>2015-03-14</aux:dataExpeCartDeIdentidade>
    <aux:nomeServidor>RAINHA ALVES DIAS</aux:nomeServidor>
    <aux:dataNascimento>1990-10-20</aux:dataNascimento>
    <aux:sexo>2</aux:sexo>
    <aux:tituloEleitor>000038720401503</aux:tituloEleitor>
    <aux:tipoEstaCivil>1</aux:tipoEstaCivil>
    <aux:pisPAsep>000016550553459</aux:pisPAsep>
    <aux:numeroOrgaoClasse>00000000</aux:numeroOrgaoClasse>
    <aux:cpfPai>99999999999</aux:cpfPai>
    <aux:nomePai>TEOTONIO ALVES DIAS</aux:nomePai>
    <aux:cpfMae>95561307304</aux:cpfMae>
    <aux:nomeMae>MARIA DA CONCEIÇÃO NUNES DIAS</aux:nomeMae>
  </aux:Servidor>
  <aux:Servidor>
    <aux:matricula>000000000000981</aux:matricula>
    <aux:cpfServidor>05010265338</aux:cpfServidor>
    <aux:rgServidor>2829659</aux:rgServidor>
    <aux:orgaoExpedidor></aux:orgaoExpedidor>
    <aux:dataExpeCartDeIdentidade>2006-02-21</aux:dataExpeCartDeIdentidade>
    <aux:nomeServidor>JOKACIA DIAS DO NASCIMENTO</aux:nomeServidor>
    <aux:dataNascimento>1991-02-05</aux:dataNascimento>
    <aux:sexo>2</aux:sexo>
    <aux:tituloEleitor>000000000000000</aux:tituloEleitor>
    <aux:tipoEstaCivil>1</aux:tipoEstaCivil>
    <aux:pisPAsep>000015353104815</aux:pisPAsep>
    <aux:numeroOrgaoClasse>00000000</aux:numeroOrgaoClasse>
    <aux:cpfPai>99999999999</aux:cpfPai>
    <aux:nomePai>JAILTON DUARTE DO NASCIMENTO</aux:nomePai>
    <aux:cpfMae>79952429304</aux:cpfMae>
    <aux:nomeMae>ANGELITA DIAS DO NASCIMENTO</aux:nomeMae>
  </aux:Servidor>
  <aux:Servidor>
    <aux:matricula>000000000000982</aux:matricula>
    <aux:cpfServidor>07421772383</aux:cpfServidor>
    <aux:rgServidor>3954353</aux:rgServidor>
    <aux:orgaoExpedidor>SSPPI</aux:orgaoExpedidor>
    <aux:dataExpeCartDeIdentidade>2013-09-12</aux:dataExpeCartDeIdentidade>
    <aux:nomeServidor>JHENIFER LOPES DE SOUSA</aux:nomeServidor>
    <aux:dataNascimento>1999-07-26</aux:dataNascimento>
    <aux:sexo>2</aux:sexo>
    <aux:tituloEleitor>000044706451562</aux:tituloEleitor>
    <aux:tipoEstaCivil>1</aux:tipoEstaCivil>
    <aux:pisPAsep>000016314329737</aux:pisPAsep>
    <aux:numeroOrgaoClasse>00000000</aux:numeroOrgaoClasse>
    <aux:cpfPai>99999999999</aux:cpfPai>
    <aux:nomePai>CÉLIO JOSÉ DE SOUSA</aux:nomePai>
    <aux:cpfMae>88411755320</aux:cpfMae>
    <aux:nomeMae> MARIA SALVADORA MENDES LOPES</aux:nomeMae>
  </aux:Servidor>
  <aux:Servidor>
    <aux:matricula>000000000000983</aux:matricula>
    <aux:cpfServidor>03653881307</aux:cpfServidor>
    <aux:rgServidor>2824827</aux:rgServidor>
    <aux:orgaoExpedidor>SSPPI</aux:orgaoExpedidor>
    <aux:dataExpeCartDeIdentidade>2006-04-06</aux:dataExpeCartDeIdentidade>
    <aux:nomeServidor>ISAILTON ALVES DIAS</aux:nomeServidor>
    <aux:dataNascimento>1982-09-28</aux:dataNascimento>
    <aux:sexo>1</aux:sexo>
    <aux:tituloEleitor>000025360431546</aux:tituloEleitor>
    <aux:tipoEstaCivil>2</aux:tipoEstaCivil>
    <aux:pisPAsep>000012819771485</aux:pisPAsep>
    <aux:numeroOrgaoClasse>00000000</aux:numeroOrgaoClasse>
    <aux:cpfPai>99999999999</aux:cpfPai>
    <aux:nomePai>GIDEVALDO DIAS MARQUES</aux:nomePai>
    <aux:cpfMae>01391608330</aux:cpfMae>
    <aux:nomeMae>IVANILDE ALVES DIAS</aux:nomeMae>
  </aux:Servidor>
</aux:CadastrosAuxiliaresSagresFolha>
